{
  "budget": "50pct",
  "results": {
    "StreamingLLM": {
      "narrativeqa": {
        "score": 25.55,
        "n": 13,
        "category": "Single-Doc QA"
      },
      "hotpotqa": {
        "score": 30.19,
        "n": 13,
        "category": "Multi-Doc QA"
      },
      "multi_news": {
        "score": 14.64,
        "n": 13,
        "category": "Summarization"
      },
      "triviaqa": {
        "score": 64.67,
        "n": 13,
        "category": "Few-Shot"
      },
      "passage_retrieval_en": {
        "score": 15.38,
        "n": 13,
        "category": "Synthetic"
      },
      "lcc": {
        "score": 13.77,
        "n": 13,
        "category": "Code"
      },
      "_category_avg": {
        "Single-Doc QA": 25.55,
        "Multi-Doc QA": 30.19,
        "Summarization": 14.64,
        "Few-Shot": 64.67,
        "Synthetic": 15.38,
        "Code": 13.77
      },
      "_overall_avg": 27.37
    },
    "SnapKV": {
      "narrativeqa": {
        "score": 27.42,
        "n": 13,
        "category": "Single-Doc QA"
      },
      "hotpotqa": {
        "score": 28.57,
        "n": 13,
        "category": "Multi-Doc QA"
      },
      "multi_news": {
        "score": 16.91,
        "n": 13,
        "category": "Summarization"
      },
      "triviaqa": {
        "score": 31.81,
        "n": 13,
        "category": "Few-Shot"
      },
      "passage_retrieval_en": {
        "score": 38.46,
        "n": 13,
        "category": "Synthetic"
      },
      "lcc": {
        "score": 4.72,
        "n": 13,
        "category": "Code"
      },
      "_category_avg": {
        "Single-Doc QA": 27.42,
        "Multi-Doc QA": 28.57,
        "Summarization": 16.91,
        "Few-Shot": 31.81,
        "Synthetic": 38.46,
        "Code": 4.72
      },
      "_overall_avg": 24.65
    },
    "PyramidKV": {
      "narrativeqa": {
        "score": 27.42,
        "n": 13,
        "category": "Single-Doc QA"
      },
      "hotpotqa": {
        "score": 25.46,
        "n": 13,
        "category": "Multi-Doc QA"
      },
      "multi_news": {
        "score": 17.63,
        "n": 13,
        "category": "Summarization"
      },
      "triviaqa": {
        "score": 31.14,
        "n": 13,
        "category": "Few-Shot"
      },
      "passage_retrieval_en": {
        "score": 23.08,
        "n": 13,
        "category": "Synthetic"
      },
      "lcc": {
        "score": 4.27,
        "n": 13,
        "category": "Code"
      },
      "_category_avg": {
        "Single-Doc QA": 27.42,
        "Multi-Doc QA": 25.46,
        "Summarization": 17.63,
        "Few-Shot": 31.14,
        "Synthetic": 23.08,
        "Code": 4.27
      },
      "_overall_avg": 21.5
    }
  }
}